svd_gdb/__init__.py
svd_gdb/gdb.py
svd_gdb/make_stub.py
svd_gdb/mutable_number.py
svd_gdb/svd_gdb.py
svd_gdb/drivers/base.py
svd_gdb/drivers/nrf5x.py
svd_gdb/drivers/stm32.py
svd_gdb/github_dl/cached.py
svd_gdb/github_dl/github_dl.py
svd_gdb/github_dl/registry.txt
svd_gdb/github_dl/revhash.txt
svd_gdb/github_dl/update_registry.py
svd_gdb-0.0.8.dist-info/LICENSE
svd_gdb-0.0.8.dist-info/METADATA
svd_gdb-0.0.8.dist-info/WHEEL
svd_gdb-0.0.8.dist-info/top_level.txt
svd_gdb-0.0.8.dist-info/RECORD
