Metadata-Version: 2.1
Name: svd_gdb
Version: 0.0.8
Summary: Python interface to SVD files through GDB
Author-email: Mark Rages <markrages@gmail.com>
Project-URL: Homepage, https://github.com/markrages/svd_gdb/
Project-URL: Bug Tracker, https://github.com/markrages/svd_gdb/issues
Classifier: Programming Language :: Python :: 3
Classifier: License :: OSI Approved :: GNU General Public License v3 (GPLv3)
Classifier: Operating System :: OS Independent
Classifier: Topic :: Scientific/Engineering :: Interface Engine/Protocol Translator
Requires-Python: >=3.6
License-File: LICENSE
Requires-Dist: pySerial
Requires-Dist: pooch
